alibabacloud_microgw20200810/__init__.py
alibabacloud_microgw20200810/client.py
alibabacloud_microgw20200810/models.py
alibabacloud_microgw20200810-20201217.dist-info/LICENSE
alibabacloud_microgw20200810-20201217.dist-info/METADATA
alibabacloud_microgw20200810-20201217.dist-info/WHEEL
alibabacloud_microgw20200810-20201217.dist-info/top_level.txt
alibabacloud_microgw20200810-20201217.dist-info/RECORD
