Metadata-Version: 2.1
Name: alibabacloud-microgw20200810
Version: 20201217
Summary: Alibaba Cloud microgw (20200810) SDK Library for Python
Home-page: https://github.com/aliyun/alibabacloud-sdk
Author: Alibaba Cloud SDK
Author-email: sdk-team@alibabacloud.com
License: Apache License 2.0
Keywords: alibabacloud_microgw20200810
Platform: any
Classifier: Development Status :: 4 - Beta
Classifier: Intended Audience :: Developers
Classifier: License :: OSI Approved :: Apache Software License
Classifier: Programming Language :: Python
Classifier: Programming Language :: Python :: 3
Classifier: Programming Language :: Python :: 3.4
Classifier: Programming Language :: Python :: 3.5
Classifier: Programming Language :: Python :: 3.6
Classifier: Programming Language :: Python :: 3.7
Classifier: Programming Language :: Python :: 3.8
Classifier: Topic :: Software Development
Requires-Dist: alibabacloud-tea-util (<1.0.0,>=0.2.0)
Requires-Dist: alibabacloud-tea-openapi (<1.0.0,>=0.1.0)
Requires-Dist: alibabacloud-openapi-util (<1.0.0,>=0.0.3)
Requires-Dist: alibabacloud-endpoint-util (<1.0.0,>=0.0.3)
